application/__init__.py
application/broker.py
application/config/__init__.py
application/config/parser.py
application/config/time_parser.py
application/devices/__init__.py
application/devices/base.py
application/devices/lytko.py
application/devices/vakio.py
application/devices/yeelink.py
mqtt_automator/__init__.py
mqtt_automator/automator.py
mqtt_automator/broker.py
mqtt_automator/config/__init__.py
mqtt_automator/config/parser.py
mqtt_automator/config/time_parser.py
mqtt_automator/devices/__init__.py
mqtt_automator/devices/base.py
mqtt_automator/devices/lytko.py
mqtt_automator/devices/vakio.py
mqtt_automator/devices/yeelink.py
mqtt_automator-0.0.4.dist-info/LICENSE
mqtt_automator-0.0.4.dist-info/METADATA
mqtt_automator-0.0.4.dist-info/WHEEL
mqtt_automator-0.0.4.dist-info/entry_points.txt
mqtt_automator-0.0.4.dist-info/top_level.txt
mqtt_automator-0.0.4.dist-info/RECORD
