Metadata-Version: 2.1
Name: mqtt-automator
Version: 0.0.4
Summary: Simple smart-home automation system. Self-hosted, LAN only. Supports Vakio Lytko and Yeelink.
Author-email: Oleg Strizhechenko <oleg.strizhechenko@gmail.com>
License: The MIT License (MIT)
Keywords: mqtt,aiomqtt,vakio,lytko,yeelink,self-hosted
Requires-Python: >=3.11
License-File: LICENSE
Requires-Dist: PyYAML ~=6.0.1
Requires-Dist: aiomqtt ~=2.1.0
Requires-Dist: paho-mqtt ~=2.1.0
Requires-Dist: pydantic ~=2.7.1
Provides-Extra: test
Requires-Dist: pre-commit ; extra == 'test'
Requires-Dist: pytest ; extra == 'test'
Requires-Dist: pylint ; extra == 'test'
